cpsms/__init__.py
cpsms/client.py
cpsms/exceptions.py
cpsms/models.py
cpsms/py.typed
cpsms_client-1.0.0.dist-info/METADATA
cpsms_client-1.0.0.dist-info/WHEEL
cpsms_client-1.0.0.dist-info/licenses/LICENSE
cpsms_client-1.0.0.dist-info/RECORD
