Metadata-Version: 2.4
Name: cpsms-client
Version: 1.0.0
Summary: Python client for the CPSMS.dk SMS Gateway API
Project-URL: Homepage, https://github.com/jetdk/cpsms-client
Project-URL: Documentation, https://github.com/jetdk/cpsms-client#readme
Project-URL: Repository, https://github.com/jetdk/cpsms-client
Project-URL: Issues, https://github.com/jetdk/cpsms-client/issues
Project-URL: Changelog, https://github.com/jetdk/cpsms-client/blob/main/CHANGELOG.md
Author-email: Jerome Thorstenson <jetdk81@gmail.com>
License-Expression: MIT
License-File: LICENSE
Keywords: api,async,client,cpsms,denmark,gateway,httpx,sms
Classifier: Development Status :: 5 - Production/Stable
Classifier: Framework :: AsyncIO
Classifier: Intended Audience :: Developers
Classifier: License :: OSI Approved :: MIT License
Classifier: Operating System :: OS Independent
Classifier: Programming Language :: Python :: 3
Classifier: Programming Language :: Python :: 3.10
Classifier: Programming Language :: Python :: 3.11
Classifier: Programming Language :: Python :: 3.12
Classifier: Programming Language :: Python :: 3.13
Classifier: Programming Language :: Python :: 3.14
Classifier: Topic :: Communications :: Telephony
Classifier: Topic :: Software Development :: Libraries :: Python Modules
Classifier: Typing :: Typed
Requires-Python: >=3.10
Requires-Dist: httpx>=0.24.0
Provides-Extra: dev
Requires-Dist: mypy>=1.0.0; extra == 'dev'
Requires-Dist: pytest-asyncio>=0.21.0; extra == 'dev'
Requires-Dist: pytest-cov>=4.0.0; extra == 'dev'
Requires-Dist: pytest>=7.0.0; extra == 'dev'
Requires-Dist: respx>=0.20.0; extra == 'dev'
Requires-Dist: ruff>=0.1.0; extra == 'dev'
